extractStructuresWithMC/__init__.py
extractStructuresWithMC/extractStructuresWithMC.py
extractStructuresWithMC/runTests.py
extractStructuresWithMC/testData.bin
extractstructuresMC-1.0.0.1.dist-info/METADATA
extractstructuresMC-1.0.0.1.dist-info/WHEEL
extractstructuresMC-1.0.0.1.dist-info/top_level.txt
extractstructuresMC-1.0.0.1.dist-info/RECORD
